MANIFEST.in
setup.py
django_simple_formwizard.egg-info/PKG-INFO
django_simple_formwizard.egg-info/SOURCES.txt
django_simple_formwizard.egg-info/dependency_links.txt
django_simple_formwizard.egg-info/not-zip-safe
django_simple_formwizard.egg-info/top_level.txt
form_wizard/__init__.py
form_wizard/__init__.pyc
form_wizard/wizard.py
form_wizard/wizard.pyc