Metadata-Version: 1.1
Name: django-simple-formwizard
Version: 0.1
Summary: Simple session based form wizard for django applications.
Home-page: https://github.com/aisayko/django-simple-formwizard
Author: Alex Isayko
Author-email: alex.isayko@gmail.com
License: MIT License
Keywords: django form wizard formwizard
Platform: any
Classifier: Development Status :: 5 - Production/Stable
Classifier: Environment :: Web Environment
Classifier: Framework :: Django
Classifier: Intended Audience :: Developers
Classifier: License :: OSI Approved :: MIT License
Classifier: Operating System :: OS Independent
Classifier: Programming Language :: Python
Classifier: Topic :: Software Development :: Libraries :: Application Frameworks
Classifier: Topic :: Software Development :: Libraries :: Python Modules
